{
	"info": {
		"_postman_id": "9fafe1f5-5b64-4721-adbf-9a5bfe12bf70",
		"name": "JPA",
		"description": "[https://github.com/AkimJemi/JPA](https://github.com/AkimJemi/JPA)",
		"schema": "https://schema.getpostman.com/json/collection/v2.0.0/collection.json"
	},
	"item": [
		{
			"name": "UserController",
			"item": [
				{
					"name": "batchAllUsers",
					"id": "c93525f1-619d-4430-9d66-d0d7741001c0",
					"protocolProfileBehavior": {
						"disableBodyPruning": true
					},
					"request": {
						"method": "POST",
						"header": [],
						"body": {
							"mode": "raw",
							"raw": "[\r\n    {\r\n        \"id\": \"5\"\r\n    }\r\n]",
							"options": {
								"raw": {
									"language": "json"
								}
							}
						},
						"url": "http://localhost:8081/user/batch/post"
					},
					"response": []
				},
				{
					"name": "userLogin",
					"id": "3199b884-b4c8-4283-a8be-509542d5b6cd",
					"protocolProfileBehavior": {
						"disableBodyPruning": true
					},
					"request": {
						"method": "POST",
						"header": [],
						"body": {
							"mode": "raw",
							"raw": "{\r\n    \"id\": 1\r\n}\r\n",
							"options": {
								"raw": {
									"language": "json"
								}
							}
						},
						"url": "http://localhost:8081/user/login"
					},
					"response": []
				},
				{
					"name": "batchAllUsers",
					"id": "09f01760-9908-4d63-880e-cdb94880993a",
					"protocolProfileBehavior": {
						"disableBodyPruning": true
					},
					"request": {
						"method": "PUT",
						"header": [],
						"url": "http://localhost:8081/user/batch/put"
					},
					"response": []
				},
				{
					"name": "findUserById",
					"id": "80db086f-8772-4fb6-ad1d-d91ec5935b94",
					"protocolProfileBehavior": {
						"disableBodyPruning": true
					},
					"request": {
						"method": "GET",
						"header": [],
						"url": {
							"raw": "http://localhost:8081/user/find?id=0",
							"protocol": "http",
							"host": [
								"localhost"
							],
							"port": "8081",
							"path": [
								"user",
								"find"
							],
							"query": [
								{
									"key": "id",
									"value": "0"
								}
							]
						}
					},
					"response": []
				},
				{
					"name": "findAllUser",
					"id": "925ab00f-8a94-4cef-a515-d3b12b7cf6cc",
					"protocolProfileBehavior": {
						"disableBodyPruning": true
					},
					"request": {
						"method": "GET",
						"header": [],
						"url": "http://localhost:8081/user/findAll"
					},
					"response": []
				},
				{
					"name": "deleteUserById",
					"id": "fd1e5ed6-2404-43d5-a244-598822aa9e83",
					"protocolProfileBehavior": {
						"disableBodyPruning": true
					},
					"request": {
						"method": "DELETE",
						"header": [],
						"url": {
							"raw": "http://localhost:8081/user/delete?id=0",
							"protocol": "http",
							"host": [
								"localhost"
							],
							"port": "8081",
							"path": [
								"user",
								"delete"
							],
							"query": [
								{
									"key": "id",
									"value": "0"
								}
							]
						}
					},
					"response": []
				},
				{
					"name": "deleteAllUsers",
					"id": "71524638-3bf8-419b-bcc7-5b76b90bd608",
					"protocolProfileBehavior": {
						"disableBodyPruning": true
					},
					"request": {
						"method": "DELETE",
						"header": [],
						"url": "http://localhost:8081/user/deleteAll"
					},
					"response": []
				}
			],
			"id": "b679151f-8a71-46c7-a350-420a304ea83e"
		},
		{
			"name": "AccountController",
			"item": [
				{
					"name": "batchAllAccounts",
					"id": "67848d7c-6cc7-444e-9b12-83383505fc82",
					"protocolProfileBehavior": {
						"disableBodyPruning": true
					},
					"request": {
						"method": "PUT",
						"header": [],
						"url": "http://localhost:8081/account/batch/put"
					},
					"response": []
				},
				{
					"name": "batchAllAccounts",
					"id": "8ba4483f-23f7-4c20-904d-4e92053191a2",
					"protocolProfileBehavior": {
						"disableBodyPruning": true
					},
					"request": {
						"method": "POST",
						"header": [],
						"url": "http://localhost:8081/account/batch/post"
					},
					"response": []
				},
				{
					"name": "findAccountById",
					"id": "3492c000-33ab-4c42-836d-220e006be0bc",
					"protocolProfileBehavior": {
						"disableBodyPruning": true
					},
					"request": {
						"method": "GET",
						"header": [],
						"url": {
							"raw": "http://localhost:8081/account/find?id=5",
							"protocol": "http",
							"host": [
								"localhost"
							],
							"port": "8081",
							"path": [
								"account",
								"find"
							],
							"query": [
								{
									"key": "id",
									"value": "5"
								}
							]
						}
					},
					"response": []
				},
				{
					"name": "updateAccountById",
					"id": "241d5a38-7ca7-4dc0-ba98-88031ee84619",
					"protocolProfileBehavior": {
						"disableBodyPruning": true
					},
					"request": {
						"method": "PATCH",
						"header": [],
						"body": {
							"mode": "raw",
							"raw": "{\r\n    \"id\": 1,\r\n    \"userId\": \"T\",\r\n    \"accountNumber\": 2415283920195,\r\n    \"accountName\": \"三井住友銀行\",\r\n    \"balance\": 125000,\r\n    \"accountType\": null\r\n}",
							"options": {
								"raw": {
									"language": "json"
								}
							}
						},
						"url": "http://localhost:8081/account/update"
					},
					"response": []
				},
				{
					"name": "findAllAccounts",
					"id": "1c0f0448-beb9-491f-8a2d-8b9a849331f4",
					"protocolProfileBehavior": {
						"disableBodyPruning": true
					},
					"request": {
						"method": "GET",
						"header": [],
						"url": "http://localhost:8081/account/findAll"
					},
					"response": []
				},
				{
					"name": "deleteAccountById",
					"id": "2f6152b3-a832-47be-a649-e0ac851923c3",
					"protocolProfileBehavior": {
						"disableBodyPruning": true
					},
					"request": {
						"method": "DELETE",
						"header": [],
						"body": {
							"mode": "raw",
							"raw": "{\r\n    \"id\": 1\r\n}",
							"options": {
								"raw": {
									"language": "json"
								}
							}
						},
						"url": "http://localhost:8081/account/delete"
					},
					"response": []
				},
				{
					"name": "deleteAllAccounts",
					"id": "9d1af548-1eda-44d2-8b91-49ae4e591ee1",
					"protocolProfileBehavior": {
						"disableBodyPruning": true
					},
					"request": {
						"method": "DELETE",
						"header": [],
						"url": "http://localhost:8081/account/deleteAll"
					},
					"response": []
				}
			],
			"id": "1c4c8853-a45e-45ee-af8f-910dc8e9e9cc"
		}
	]
}